{
  "Taxations": [
    {
      "Name": "",
      "Alpha2": "",
      "Alpha3": "",
      "CorporateTax": null,
      "CapitalGainsTax": null,
      "IncomeTax": null,
      "LumpsumpTax": null,
      "WealthTax": null
    },
    {
      "Name": "#REF!",
      "Alpha2": "#REF!",
      "Alpha3": "#REF!",
      "CorporateTax": null,
      "CapitalGainsTax": null,
      "IncomeTax": null,
      "LumpsumpTax": null,
      "WealthTax": null
    },
    {
      "Name": "Afghanistan",
      "Alpha2": "AF",
      "Alpha3": "AFG",
      "CorporateTax": {
        "Rate": 20.00,
        "LastUpdated": "2022-11-14T17:51:23.8905875+04:00",
        "Brackets": []
      },
      "CapitalGainsTax": null,
      "IncomeTax": null,
      "LumpsumpTax": null,
      "WealthTax": null
    },
    {
      "Name": "Albania",
      "Alpha2": "AL",
      "Alpha3": "ALB",
      "CorporateTax": {
        "Rate": 15.00,
        "LastUpdated": "2022-11-14T17:51:23.8906969+04:00",
        "Brackets": []
      },
      "CapitalGainsTax": {
        "Rate": 15.00,
        "LastUpdated": "2022-11-14T17:51:23.8731374+04:00",
        "Brackets": []
      },
      "IncomeTax": null,
      "LumpsumpTax": null,
      "WealthTax": null
    },
    {
      "Name": "Algeria",
      "Alpha2": "DZ",
      "Alpha3": "DZA",
      "CorporateTax": {
        "Rate": 26.00,
        "LastUpdated": "2022-11-14T17:51:23.8907098+04:00",
        "Brackets": []
      },
      "CapitalGainsTax": {
        "Rate": 15.00,
        "LastUpdated": "2022-11-14T17:51:23.8745207+04:00",
        "Brackets": []
      },
      "IncomeTax": null,
      "LumpsumpTax": null,
      "WealthTax": null
    },
    {
      "Name": "American Samoa",
      "Alpha2": "AS",
      "Alpha3": "ASM",
      "CorporateTax": {
        "Rate": 27.00,
        "LastUpdated": "2022-11-14T17:51:23.8907245+04:00",
        "Brackets": []
      },
      "CapitalGainsTax": null,
      "IncomeTax": null,
      "LumpsumpTax": null,
      "WealthTax": null
    },
    {
      "Name": "Andorra",
      "Alpha2": "AD",
      "Alpha3": "AND",
      "CorporateTax": {
        "Rate": 10.00,
        "LastUpdated": "2022-11-14T17:51:23.8907351+04:00",
        "Brackets": []
      },
      "CapitalGainsTax": {
        "Rate": 10.00,
        "LastUpdated": "2022-11-14T17:51:23.8745446+04:00",
        "Brackets": []
      },
      "IncomeTax": null,
      "LumpsumpTax": null,
      "WealthTax": null
    },
    {
      "Name": "Angola",
      "Alpha2": "AO",
      "Alpha3": "AGO",
      "CorporateTax": {
        "Rate": 25.00,
        "LastUpdated": "2022-11-14T17:51:23.8907455+04:00",
        "Brackets": []
      },
      "CapitalGainsTax": {
        "Rate": 10.00,
        "LastUpdated": "2022-11-14T17:51:23.8745608+04:00",
        "Brackets": []
      },
      "IncomeTax": null,
      "LumpsumpTax": null,
      "WealthTax": null
    },
    {
      "Name": "Anguilla",
      "Alpha2": "AI",
      "Alpha3": "AIA",
      "CorporateTax": {
        "Rate": 0.00,
        "LastUpdated": "2022-11-14T17:51:23.8907583+04:00",
        "Brackets": []
      },
      "CapitalGainsTax": {
        "Rate": 0.00,
        "LastUpdated": "2022-11-14T17:51:23.8745723+04:00",
        "Brackets": []
      },
      "IncomeTax": null,
      "LumpsumpTax": null,
      "WealthTax": null
    },
    {
      "Name": "Argentina",
      "Alpha2": "AR",
      "Alpha3": "ARG",
      "CorporateTax": {
        "Rate": 35.00,
        "LastUpdated": "2022-11-14T17:51:23.8928201+04:00",
        "Brackets": []
      },
      "CapitalGainsTax": {
        "Rate": 15.00,
        "LastUpdated": "2022-11-14T17:51:23.8745848+04:00",
        "Brackets": []
      },
      "IncomeTax": null,
      "LumpsumpTax": null,
      "WealthTax": {
        "Rate": 1.75,
        "Base": 300000000.0,
        "Comments": "Higher rates for abroad assets",
        "Currency": null,
        "LastUpdated": "2022-11-14T17:51:23.991144+04:00",
        "Brackets": []
      }
    },
    {
      "Name": "Armenia",
      "Alpha2": "AM",
      "Alpha3": "ARM",
      "CorporateTax": {
        "Rate": 18.00,
        "LastUpdated": "2022-11-14T17:51:23.8928393+04:00",
        "Brackets": []
      },
      "CapitalGainsTax": {
        "Rate": 18.0,
        "LastUpdated": "2022-11-14T17:51:23.8745988+04:00",
        "Brackets": []
      },
      "IncomeTax": null,
      "LumpsumpTax": null,
      "WealthTax": null
    },
    {
      "Name": "Australia",
      "Alpha2": "AU",
      "Alpha3": "AUS",
      "CorporateTax": {
        "Rate": 30.00,
        "LastUpdated": "2022-11-14T17:51:23.8928527+04:00",
        "Brackets": []
      },
      "CapitalGainsTax": null,
      "IncomeTax": null,
      "LumpsumpTax": null,
      "WealthTax": null
    },
    {
      "Name": "Austria",
      "Alpha2": "AT",
      "Alpha3": "AUT",
      "CorporateTax": {
        "Rate": 25.00,
        "LastUpdated": "2022-11-14T17:51:23.8928633+04:00",
        "Brackets": []
      },
      "CapitalGainsTax": null,
      "IncomeTax": null,
      "LumpsumpTax": null,
      "WealthTax": null
    },
    {
      "Name": "Azerbaijan",
      "Alpha2": "AZ",
      "Alpha3": "AZE",
      "CorporateTax": {
        "Rate": 20.00,
        "LastUpdated": "2022-11-14T17:51:23.8928771+04:00",
        "Brackets": []
      },
      "CapitalGainsTax": {
        "Rate": 20.00,
        "LastUpdated": "2022-11-14T17:51:23.8746368+04:00",
        "Brackets": []
      },
      "IncomeTax": null,
      "LumpsumpTax": null,
      "WealthTax": null
    },
    {
      "Name": "Bahamas",
      "Alpha2": "BS",
      "Alpha3": "BHS",
      "CorporateTax": {
        "Rate": 0.00,
        "LastUpdated": "2022-11-14T17:51:23.892888+04:00",
        "Brackets": []
      },
      "CapitalGainsTax": {
        "Rate": 0.00,
        "LastUpdated": "2022-11-14T17:51:23.8746482+04:00",
        "Brackets": []
      },
      "IncomeTax": null,
      "LumpsumpTax": null,
      "WealthTax": null
    },
    {
      "Name": "Bahrain",
      "Alpha2": "BH",
      "Alpha3": "BHR",
      "CorporateTax": {
        "Rate": 0.00,
        "LastUpdated": "2022-11-14T17:51:23.8928989+04:00",
        "Brackets": []
      },
      "CapitalGainsTax": {
        "Rate": 0.00,
        "LastUpdated": "2022-11-14T17:51:23.8746624+04:00",
        "Brackets": []
      },
      "IncomeTax": null,
      "LumpsumpTax": null,
      "WealthTax": null
    },
    {
      "Name": "Bangladesh",
      "Alpha2": "BD",
      "Alpha3": "BGD",
      "CorporateTax": {
        "Rate": 30.00,
        "LastUpdated": "2022-11-14T17:51:23.8929136+04:00",
        "Brackets": []
      },
      "CapitalGainsTax": {
        "Rate": 15.00,
        "LastUpdated": "2022-11-14T17:51:23.8746737+04:00",
        "Brackets": []
      },
      "IncomeTax": null,
      "LumpsumpTax": null,
      "WealthTax": null
    },
    {
      "Name": "Barbados",
      "Alpha2": "BB",
      "Alpha3": "BRB",
      "CorporateTax": {
        "Rate": 5.50,
        "LastUpdated": "2022-11-14T17:51:23.8929266+04:00",
        "Brackets": []
      },
      "CapitalGainsTax": {
        "Rate": 0.00,
        "LastUpdated": "2022-11-14T17:51:23.8746851+04:00",
        "Brackets": []
      },
      "IncomeTax": null,
      "LumpsumpTax": null,
      "WealthTax": null
    },
    {
      "Name": "Belarus",
      "Alpha2": "BY",
      "Alpha3": "BLR",
      "CorporateTax": null,
      "CapitalGainsTax": null,
      "IncomeTax": null,
      "LumpsumpTax": null,
      "WealthTax": null
    },
    {
      "Name": "Belgium",
      "Alpha2": "BE",
      "Alpha3": "BEL",
      "CorporateTax": {
        "Rate": 25.0,
        "LastUpdated": "2022-11-14T17:51:23.8929509+04:00",
        "Brackets": []
      },
      "CapitalGainsTax": {
        "Rate": 16.50,
        "LastUpdated": "2022-11-14T17:51:23.8747125+04:00",
        "Brackets": []
      },
      "IncomeTax": null,
      "LumpsumpTax": null,
      "WealthTax": {
        "Rate": 0.15,
        "Base": 1000000.0,
        "Comments": "",
        "Currency": null,
        "LastUpdated": "2022-11-14T17:51:23.9913793+04:00",
        "Brackets": []
      }
    },
    {
      "Name": "Belize",
      "Alpha2": "BZ",
      "Alpha3": "BLZ",
      "CorporateTax": {
        "Rate": 1.75,
        "LastUpdated": "2022-11-14T17:51:23.8929633+04:00",
        "Brackets": []
      },
      "CapitalGainsTax": {
        "Rate": 0.0,
        "LastUpdated": "2022-11-14T17:51:23.8747266+04:00",
        "Brackets": []
      },
      "IncomeTax": null,
      "LumpsumpTax": null,
      "WealthTax": null
    },
    {
      "Name": "Benin",
      "Alpha2": "BJ",
      "Alpha3": "BEN",
      "CorporateTax": null,
      "CapitalGainsTax": null,
      "IncomeTax": null,
      "LumpsumpTax": null,
      "WealthTax": null
    },
    {
      "Name": "Bermuda",
      "Alpha2": "BM",
      "Alpha3": "BMU",
      "CorporateTax": {
        "Rate": 7.00,
        "LastUpdated": "2022-11-14T17:51:23.8929883+04:00",
        "Brackets": []
      },
      "CapitalGainsTax": {
        "Rate": 0.00,
        "LastUpdated": "2022-11-14T17:51:23.8747537+04:00",
        "Brackets": []
      },
      "IncomeTax": null,
      "LumpsumpTax": null,
      "WealthTax": null
    },
    {
      "Name": "Bhutan",
      "Alpha2": "BT",
      "Alpha3": "BTN",
      "CorporateTax": {
        "Rate": 25.00,
        "LastUpdated": "2022-11-14T17:51:23.893002+04:00",
        "Brackets": []
      },
      "CapitalGainsTax": null,
      "IncomeTax": null,
      "LumpsumpTax": null,
      "WealthTax": null
    },
    {
      "Name": "Bolivia",
      "Alpha2": "BO",
      "Alpha3": "BOL",
      "CorporateTax": {
        "Rate": 25.00,
        "LastUpdated": "2022-11-14T17:51:23.8930137+04:00",
        "Brackets": []
      },
      "CapitalGainsTax": {
        "Rate": 25.00,
        "LastUpdated": "2022-11-14T17:51:23.8747779+04:00",
        "Brackets": []
      },
      "IncomeTax": null,
      "LumpsumpTax": null,
      "WealthTax": null
    },
    {
      "Name": "Bosnia and Herzegovina",
      "Alpha2": "BA",
      "Alpha3": "BIH",
      "CorporateTax": {
        "Rate": 10.00,
        "LastUpdated": "2022-11-14T17:51:23.8930271+04:00",
        "Brackets": []
      },
      "CapitalGainsTax": {
        "Rate": 10.00,
        "LastUpdated": "2022-11-14T17:51:23.8747946+04:00",
        "Brackets": []
      },
      "IncomeTax": null,
      "LumpsumpTax": null,
      "WealthTax": null
    },
    {
      "Name": "Botswana",
      "Alpha2": "BW",
      "Alpha3": "BWA",
      "CorporateTax": {
        "Rate": 22.00,
        "LastUpdated": "2022-11-14T17:51:23.8930464+04:00",
        "Brackets": []
      },
      "CapitalGainsTax": null,
      "IncomeTax": null,
      "LumpsumpTax": null,
      "WealthTax": null
    },
    {
      "Name": "Brazil",
      "Alpha2": "BR",
      "Alpha3": "BRA",
      "CorporateTax": {
        "Rate": 34.00,
        "LastUpdated": "2022-11-14T17:51:23.8930614+04:00",
        "Brackets": []
      },
      "CapitalGainsTax": null,
      "IncomeTax": null,
      "LumpsumpTax": null,
      "WealthTax": null
    },
    {
      "Name": "Brunei Darussalam",
      "Alpha2": "BN",
      "Alpha3": "BRN",
      "CorporateTax": {
        "Rate": 18.50,
        "LastUpdated": "2022-11-14T17:51:23.8930766+04:00",
        "Brackets": []
      },
      "CapitalGainsTax": {
        "Rate": 0.00,
        "LastUpdated": "2022-11-14T17:51:23.8748351+04:00",
        "Brackets": []
      },
      "IncomeTax": null,
      "LumpsumpTax": null,
      "WealthTax": null
    },
    {
      "Name": "Bulgaria",
      "Alpha2": "BG",
      "Alpha3": "BGR",
      "CorporateTax": {
        "Rate": 10.00,
        "LastUpdated": "2022-11-14T17:51:23.8930914+04:00",
        "Brackets": []
      },
      "CapitalGainsTax": {
        "Rate": 10.00,
        "LastUpdated": "2022-11-14T17:51:23.8748497+04:00",
        "Brackets": []
      },
      "IncomeTax": null,
      "LumpsumpTax": null,
      "WealthTax": null
    },
    {
      "Name": "Burkina Faso",
      "Alpha2": "BF",
      "Alpha3": "BFA",
      "CorporateTax": {
        "Rate": 27.50,
        "LastUpdated": "2022-11-14T17:51:23.8931136+04:00",
        "Brackets": []
      },
      "CapitalGainsTax": null,
      "IncomeTax": null,
      "LumpsumpTax": null,
      "WealthTax": null
    },
    {
      "Name": "Burundi",
      "Alpha2": "BI",
      "Alpha3": "BDI",
      "CorporateTax": {
        "Rate": 30.00,
        "LastUpdated": "2022-11-14T17:51:23.8931261+04:00",
        "Brackets": []
      },
      "CapitalGainsTax": {
        "Rate": 15.00,
        "LastUpdated": "2022-11-14T17:51:23.8748777+04:00",
        "Brackets": []
      },
      "IncomeTax": null,
      "LumpsumpTax": null,
      "WealthTax": null
    },
    {
      "Name": "Cambodia",
      "Alpha2": "KH",
      "Alpha3": "KHM",
      "CorporateTax": {
        "Rate": 20.00,
        "LastUpdated": "2022-11-14T17:51:23.8931419+04:00",
        "Brackets": []
      },
      "CapitalGainsTax": {
        "Rate": 20.00,
        "LastUpdated": "2022-11-14T17:51:23.8748903+04:00",
        "Brackets": []
      },
      "IncomeTax": null,
      "LumpsumpTax": null,
      "WealthTax": null
    },
    {
      "Name": "Cameroon",
      "Alpha2": "CM",
      "Alpha3": "CMR",
      "CorporateTax": {
        "Rate": 33.00,
        "LastUpdated": "2022-11-14T17:51:23.893155+04:00",
        "Brackets": []
      },
      "CapitalGainsTax": {
        "Rate": 16.50,
        "LastUpdated": "2022-11-14T17:51:23.8749052+04:00",
        "Brackets": []
      },
      "IncomeTax": null,
      "LumpsumpTax": null,
      "WealthTax": null
    },
    {
      "Name": "Canada",
      "Alpha2": "CA",
      "Alpha3": "CAN",
      "CorporateTax": {
        "Rate": 38.00,
        "LastUpdated": "2022-11-14T17:51:23.8931707+04:00",
        "Brackets": []
      },
      "CapitalGainsTax": null,
      "IncomeTax": null,
      "LumpsumpTax": null,
      "WealthTax": null
    },
    {
      "Name": "Central African Republic",
      "Alpha2": "CF",
      "Alpha3": "CAF",
      "CorporateTax": {
        "Rate": 30.00,
        "LastUpdated": "2022-11-14T17:51:23.893183+04:00",
        "Brackets": []
      },
      "CapitalGainsTax": null,
      "IncomeTax": null,
      "LumpsumpTax": null,
      "WealthTax": null
    },
    {
      "Name": "Chad",
      "Alpha2": "TD",
      "Alpha3": "TCD",
      "CorporateTax": {
        "Rate": 35.00,
        "LastUpdated": "2022-11-14T17:51:23.8931978+04:00",
        "Brackets": []
      },
      "CapitalGainsTax": {
        "Rate": 20.00,
        "LastUpdated": "2022-11-14T17:51:23.8749474+04:00",
        "Brackets": []
      },
      "IncomeTax": null,
      "LumpsumpTax": null,
      "WealthTax": null
    },
    {
      "Name": "Chile",
      "Alpha2": "CL",
      "Alpha3": "CHL",
      "CorporateTax": {
        "Rate": 27.00,
        "LastUpdated": "2022-11-14T17:51:23.8932103+04:00",
        "Brackets": []
      },
      "CapitalGainsTax": null,
      "IncomeTax": null,
      "LumpsumpTax": null,
      "WealthTax": null
    },
    {
      "Name": "China",
      "Alpha2": "CN",
      "Alpha3": "CHN",
      "CorporateTax": {
        "Rate": 25.00,
        "LastUpdated": "2022-11-14T17:51:23.8932249+04:00",
        "Brackets": []
      },
      "CapitalGainsTax": null,
      "IncomeTax": null,
      "LumpsumpTax": null,
      "WealthTax": null
    },
    {
      "Name": "Colombia",
      "Alpha2": "CO",
      "Alpha3": "COL",
      "CorporateTax": {
        "Rate": 35.00,
        "LastUpdated": "2022-11-14T17:51:23.8932377+04:00",
        "Brackets": []
      },
      "CapitalGainsTax": null,
      "IncomeTax": null,
      "LumpsumpTax": null,
      "WealthTax": {
        "Rate": 1.0,
        "Base": 5000000000.0,
        "Comments": "",
        "Currency": null,
        "LastUpdated": "2022-11-14T17:51:23.9916421+04:00",
        "Brackets": []
      }
    },
    {
      "Name": "Congo",
      "Alpha2": "CG",
      "Alpha3": "COG",
      "CorporateTax": {
        "Rate": 30.00,
        "LastUpdated": "2022-11-14T17:51:23.8932534+04:00",
        "Brackets": []
      },
      "CapitalGainsTax": null,
      "IncomeTax": null,
      "LumpsumpTax": null,
      "WealthTax": null
    },
    {
      "Name": "Costa Rica",
      "Alpha2": "CR",
      "Alpha3": "CRI",
      "CorporateTax": {
        "Rate": 30.00,
        "LastUpdated": "2022-11-14T17:51:23.8932689+04:00",
        "Brackets": []
      },
      "CapitalGainsTax": null,
      "IncomeTax": null,
      "LumpsumpTax": null,
      "WealthTax": null
    },
    {
      "Name": "Côte dIvoire",
      "Alpha2": "CI",
      "Alpha3": "CIV",
      "CorporateTax": {
        "Rate": 25.00,
        "LastUpdated": "2022-11-14T17:51:23.8932836+04:00",
        "Brackets": []
      },
      "CapitalGainsTax": null,
      "IncomeTax": null,
      "LumpsumpTax": null,
      "WealthTax": null
    },
    {
      "Name": "Croatia",
      "Alpha2": "HR",
      "Alpha3": "HRV",
      "CorporateTax": {
        "Rate": 18.00,
        "LastUpdated": "2022-11-14T17:51:23.8932969+04:00",
        "Brackets": []
      },
      "CapitalGainsTax": null,
      "IncomeTax": null,
      "LumpsumpTax": null,
      "WealthTax": null
    },
    {
      "Name": "Cuba",
      "Alpha2": "CU",
      "Alpha3": "CUB",
      "CorporateTax": {
        "Rate": 35.00,
        "LastUpdated": "2022-11-14T17:51:23.893313+04:00",
        "Brackets": []
      },
      "CapitalGainsTax": null,
      "IncomeTax": null,
      "LumpsumpTax": null,
      "WealthTax": null
    },
    {
      "Name": "Cyprus",
      "Alpha2": "CY",
      "Alpha3": "CYP",
      "CorporateTax": {
        "Rate": 12.50,
        "LastUpdated": "2022-11-14T17:51:23.8933264+04:00",
        "Brackets": []
      },
      "CapitalGainsTax": {
        "Rate": 20.00,
        "LastUpdated": "2022-11-14T17:51:23.875122+04:00",
        "Brackets": []
      },
      "IncomeTax": null,
      "LumpsumpTax": null,
      "WealthTax": null
    },
    {
      "Name": "Czechia",
      "Alpha2": "CZ",
      "Alpha3": "CZE",
      "CorporateTax": {
        "Rate": 19.00,
        "LastUpdated": "2022-11-14T17:51:23.8933431+04:00",
        "Brackets": []
      },
      "CapitalGainsTax": null,
      "IncomeTax": null,
      "LumpsumpTax": null,
      "WealthTax": null
    },
    {
      "Name": "Denmark",
      "Alpha2": "DK",
      "Alpha3": "DNK",
      "CorporateTax": {
        "Rate": 22.00,
        "LastUpdated": "2022-11-14T17:51:23.8933651+04:00",
        "Brackets": []
      },
      "CapitalGainsTax": null,
      "IncomeTax": null,
      "LumpsumpTax": null,
      "WealthTax": null
    },
    {
      "Name": "Djibouti",
      "Alpha2": "DJ",
      "Alpha3": "DJI",
      "CorporateTax": null,
      "CapitalGainsTax": {
        "Rate": 5.00,
        "LastUpdated": "2022-11-14T17:51:23.8751682+04:00",
        "Brackets": []
      },
      "IncomeTax": null,
      "LumpsumpTax": null,
      "WealthTax": null
    },
    {
      "Name": "Dominica",
      "Alpha2": "DM",
      "Alpha3": "DMA",
      "CorporateTax": {
        "Rate": 25.00,
        "LastUpdated": "2022-11-14T17:51:23.8933933+04:00",
        "Brackets": []
      },
      "CapitalGainsTax": {
        "Rate": 0.00,
        "LastUpdated": "2022-11-14T17:51:23.8751817+04:00",
        "Brackets": []
      },
      "IncomeTax": null,
      "LumpsumpTax": null,
      "WealthTax": null
    },
    {
      "Name": "Dominican Republic",
      "Alpha2": "DO",
      "Alpha3": "DOM",
      "CorporateTax": {
        "Rate": 27.00,
        "LastUpdated": "2022-11-14T17:51:23.893407+04:00",
        "Brackets": []
      },
      "CapitalGainsTax": null,
      "IncomeTax": null,
      "LumpsumpTax": null,
      "WealthTax": null
    },
    {
      "Name": "Ecuador",
      "Alpha2": "EC",
      "Alpha3": "ECU",
      "CorporateTax": {
        "Rate": 28.00,
        "LastUpdated": "2022-11-14T17:51:23.8934268+04:00",
        "Brackets": []
      },
      "CapitalGainsTax": {
        "Rate": 10.00,
        "LastUpdated": "2022-11-14T17:51:23.8752124+04:00",
        "Brackets": []
      },
      "IncomeTax": null,
      "LumpsumpTax": null,
      "WealthTax": null
    },
    {
      "Name": "Egypt",
      "Alpha2": "EG",
      "Alpha3": "EGY",
      "CorporateTax": {
        "Rate": 22.50,
        "LastUpdated": "2022-11-14T17:51:23.8934444+04:00",
        "Brackets": []
      },
      "CapitalGainsTax": {
        "Rate": 22.50,
        "LastUpdated": "2022-11-14T17:51:23.8752289+04:00",
        "Brackets": []
      },
      "IncomeTax": null,
      "LumpsumpTax": null,
      "WealthTax": null
    },
    {
      "Name": "El Salvador",
      "Alpha2": "SV",
      "Alpha3": "SLV",
      "CorporateTax": {
        "Rate": 30.00,
        "LastUpdated": "2022-11-14T17:51:23.8934599+04:00",
        "Brackets": []
      },
      "CapitalGainsTax": {
        "Rate": 10.00,
        "LastUpdated": "2022-11-14T17:51:23.8752443+04:00",
        "Brackets": []
      },
      "IncomeTax": null,
      "LumpsumpTax": null,
      "WealthTax": null
    },
    {
      "Name": "Equatorial Guinea",
      "Alpha2": "GQ",
      "Alpha3": "GNQ",
      "CorporateTax": {
        "Rate": 35.00,
        "LastUpdated": "2022-11-14T17:51:23.8934757+04:00",
        "Brackets": []
      },
      "CapitalGainsTax": {
        "Rate": 35.00,
        "LastUpdated": "2022-11-14T17:51:23.8752887+04:00",
        "Brackets": []
      },
      "IncomeTax": null,
      "LumpsumpTax": null,
      "WealthTax": null
    },
    {
      "Name": "Eritrea",
      "Alpha2": "ER",
      "Alpha3": "ERI",
      "CorporateTax": {
        "Rate": 34.00,
        "LastUpdated": "2022-11-14T17:51:23.8934899+04:00",
        "Brackets": []
      },
      "CapitalGainsTax": {
        "Rate": 34.00,
        "LastUpdated": "2022-11-14T17:51:23.8753088+04:00",
        "Brackets": []
      },
      "IncomeTax": null,
      "LumpsumpTax": null,
      "WealthTax": null
    },
    {
      "Name": "Estonia",
      "Alpha2": "EE",
      "Alpha3": "EST",
      "CorporateTax": {
        "Rate": 20.00,
        "LastUpdated": "2022-11-14T17:51:23.8935063+04:00",
        "Brackets": []
      },
      "CapitalGainsTax": {
        "Rate": 20.00,
        "LastUpdated": "2022-11-14T17:51:23.8753232+04:00",
        "Brackets": []
      },
      "IncomeTax": null,
      "LumpsumpTax": null,
      "WealthTax": null
    },
    {
      "Name": "Ethiopia",
      "Alpha2": "ET",
      "Alpha3": "ETH",
      "CorporateTax": {
        "Rate": 30.00,
        "LastUpdated": "2022-11-14T17:51:23.8935232+04:00",
        "Brackets": []
      },
      "CapitalGainsTax": null,
      "IncomeTax": null,
      "LumpsumpTax": null,
      "WealthTax": null
    },
    {
      "Name": "Faroe Islands",
      "Alpha2": "FO",
      "Alpha3": "FRO",
      "CorporateTax": {
        "Rate": 18.00,
        "LastUpdated": "2022-11-14T17:51:23.8935381+04:00",
        "Brackets": []
      },
      "CapitalGainsTax": null,
      "IncomeTax": null,
      "LumpsumpTax": null,
      "WealthTax": null
    },
    {
      "Name": "Fiji",
      "Alpha2": "FJ",
      "Alpha3": "FJI",
      "CorporateTax": {
        "Rate": 20.00,
        "LastUpdated": "2022-11-14T17:51:23.8935562+04:00",
        "Brackets": []
      },
      "CapitalGainsTax": {
        "Rate": 10.00,
        "LastUpdated": "2022-11-14T17:51:23.8753712+04:00",
        "Brackets": []
      },
      "IncomeTax": null,
      "LumpsumpTax": null,
      "WealthTax": null
    },
    {
      "Name": "Finland",
      "Alpha2": "FI",
      "Alpha3": "FIN",
      "CorporateTax": {
        "Rate": 20.00,
        "LastUpdated": "2022-11-14T17:51:23.8935706+04:00",
        "Brackets": []
      },
      "CapitalGainsTax": null,
      "IncomeTax": null,
      "LumpsumpTax": null,
      "WealthTax": null
    },
    {
      "Name": "France",
      "Alpha2": "FR",
      "Alpha3": "FRA",
      "CorporateTax": {
        "Rate": 30.00,
        "LastUpdated": "2022-11-14T17:51:23.8935892+04:00",
        "Brackets": []
      },
      "CapitalGainsTax": null,
      "IncomeTax": null,
      "LumpsumpTax": null,
      "WealthTax": {
        "Rate": 1.50,
        "Base": 10000000.0,
        "Comments": "",
        "Currency": null,
        "LastUpdated": "2022-11-14T17:51:23.9920099+04:00",
        "Brackets": []
      }
    },
    {
      "Name": "Gabon",
      "Alpha2": "GA",
      "Alpha3": "GAB",
      "CorporateTax": {
        "Rate": 15.00,
        "LastUpdated": "2022-11-14T17:51:23.8936057+04:00",
        "Brackets": []
      },
      "CapitalGainsTax": null,
      "IncomeTax": null,
      "LumpsumpTax": null,
      "WealthTax": null
    },
    {
      "Name": "Gambia",
      "Alpha2": "GM",
      "Alpha3": "GMB",
      "CorporateTax": {
        "Rate": 27.00,
        "LastUpdated": "2022-11-14T17:51:23.8936202+04:00",
        "Brackets": []
      },
      "CapitalGainsTax": null,
      "IncomeTax": null,
      "LumpsumpTax": null,
      "WealthTax": null
    },
    {
      "Name": "Georgia",
      "Alpha2": "GE",
      "Alpha3": "GEO",
      "CorporateTax": {
        "Rate": 15.00,
        "LastUpdated": "2022-11-14T17:51:23.8936375+04:00",
        "Brackets": []
      },
      "CapitalGainsTax": null,
      "IncomeTax": null,
      "LumpsumpTax": null,
      "WealthTax": null
    },
    {
      "Name": "Germany",
      "Alpha2": "DE",
      "Alpha3": "DEU",
      "CorporateTax": {
        "Rate": 15.83,
        "LastUpdated": "2022-11-14T17:51:23.8936543+04:00",
        "Brackets": []
      },
      "CapitalGainsTax": null,
      "IncomeTax": null,
      "LumpsumpTax": null,
      "WealthTax": null
    },
    {
      "Name": "Ghana",
      "Alpha2": "GH",
      "Alpha3": "GHA",
      "CorporateTax": {
        "Rate": 25.00,
        "LastUpdated": "2022-11-14T17:51:23.8936697+04:00",
        "Brackets": []
      },
      "CapitalGainsTax": null,
      "IncomeTax": null,
      "LumpsumpTax": null,
      "WealthTax": null
    },
    {
      "Name": "Gibraltar",
      "Alpha2": "GI",
      "Alpha3": "GIB",
      "CorporateTax": null,
      "CapitalGainsTax": null,
      "IncomeTax": null,
      "LumpsumpTax": {
        "Amount": 120000.0,
        "Currency": null,
        "Rate": 0.0,
        "LastUpdated": "2022-11-14T17:51:23.933387+04:00"
      },
      "WealthTax": null
    },
    {
      "Name": "Greece",
      "Alpha2": "GR",
      "Alpha3": "GRC",
      "CorporateTax": {
        "Rate": 22.00,
        "LastUpdated": "2022-11-14T17:51:23.8937033+04:00",
        "Brackets": []
      },
      "CapitalGainsTax": null,
      "IncomeTax": null,
      "LumpsumpTax": {
        "Amount": 100000.0,
        "Currency": null,
        "Rate": 0.0,
        "LastUpdated": "2022-11-14T17:51:23.9335413+04:00"
      },
      "WealthTax": null
    },
    {
      "Name": "Greenland",
      "Alpha2": "GL",
      "Alpha3": "GRL",
      "CorporateTax": {
        "Rate": 25.00,
        "LastUpdated": "2022-11-14T17:51:23.8937195+04:00",
        "Brackets": []
      },
      "CapitalGainsTax": null,
      "IncomeTax": null,
      "LumpsumpTax": null,
      "WealthTax": null
    },
    {
      "Name": "Grenada",
      "Alpha2": "GD",
      "Alpha3": "GRD",
      "CorporateTax": {
        "Rate": 12.50,
        "LastUpdated": "2022-11-14T17:51:23.8937367+04:00",
        "Brackets": []
      },
      "CapitalGainsTax": null,
      "IncomeTax": null,
      "LumpsumpTax": null,
      "WealthTax": null
    },
    {
      "Name": "Guam",
      "Alpha2": "GU",
      "Alpha3": "GUM",
      "CorporateTax": {
        "Rate": 21.00,
        "LastUpdated": "2022-11-14T17:51:23.8937553+04:00",
        "Brackets": []
      },
      "CapitalGainsTax": null,
      "IncomeTax": null,
      "LumpsumpTax": null,
      "WealthTax": null
    },
    {
      "Name": "Guatemala",
      "Alpha2": "GT",
      "Alpha3": "GTM",
      "CorporateTax": {
        "Rate": 25.00,
        "LastUpdated": "2022-11-14T17:51:23.8937738+04:00",
        "Brackets": []
      },
      "CapitalGainsTax": null,
      "IncomeTax": null,
      "LumpsumpTax": null,
      "WealthTax": null
    },
    {
      "Name": "Guinea",
      "Alpha2": "GN",
      "Alpha3": "GIN",
      "CorporateTax": {
        "Rate": 35.00,
        "LastUpdated": "2022-11-14T17:51:23.8937891+04:00",
        "Brackets": []
      },
      "CapitalGainsTax": null,
      "IncomeTax": null,
      "LumpsumpTax": null,
      "WealthTax": null
    },
    {
      "Name": "Guinea-Bissau",
      "Alpha2": "GW",
      "Alpha3": "GNB",
      "CorporateTax": {
        "Rate": 25.00,
        "LastUpdated": "2022-11-14T17:51:23.8938066+04:00",
        "Brackets": []
      },
      "CapitalGainsTax": null,
      "IncomeTax": null,
      "LumpsumpTax": null,
      "WealthTax": null
    },
    {
      "Name": "Guyana",
      "Alpha2": "GY",
      "Alpha3": "GUY",
      "CorporateTax": {
        "Rate": 45.00,
        "LastUpdated": "2022-11-14T17:51:23.8938251+04:00",
        "Brackets": []
      },
      "CapitalGainsTax": null,
      "IncomeTax": null,
      "LumpsumpTax": null,
      "WealthTax": null
    },
    {
      "Name": "Haiti",
      "Alpha2": "HT",
      "Alpha3": "HTI",
      "CorporateTax": {
        "Rate": 30.00,
        "LastUpdated": "2022-11-14T17:51:23.8938409+04:00",
        "Brackets": []
      },
      "CapitalGainsTax": null,
      "IncomeTax": null,
      "LumpsumpTax": null,
      "WealthTax": null
    },
    {
      "Name": "Honduras",
      "Alpha2": "HN",
      "Alpha3": "HND",
      "CorporateTax": {
        "Rate": 25.00,
        "LastUpdated": "2022-11-14T17:51:23.8938585+04:00",
        "Brackets": []
      },
      "CapitalGainsTax": null,
      "IncomeTax": null,
      "LumpsumpTax": null,
      "WealthTax": null
    },
    {
      "Name": "Hong Kong",
      "Alpha2": "HK",
      "Alpha3": "HKG",
      "CorporateTax": {
        "Rate": 16.50,
        "LastUpdated": "2022-11-14T17:51:23.8938767+04:00",
        "Brackets": []
      },
      "CapitalGainsTax": null,
      "IncomeTax": null,
      "LumpsumpTax": null,
      "WealthTax": null
    },
    {
      "Name": "Hungary",
      "Alpha2": "HU",
      "Alpha3": "HUN",
      "CorporateTax": {
        "Rate": 9.00,
        "LastUpdated": "2022-11-14T17:51:23.8938943+04:00",
        "Brackets": []
      },
      "CapitalGainsTax": null,
      "IncomeTax": null,
      "LumpsumpTax": null,
      "WealthTax": null
    },
    {
      "Name": "Iceland",
      "Alpha2": "IS",
      "Alpha3": "ISL",
      "CorporateTax": {
        "Rate": 20.00,
        "LastUpdated": "2022-11-14T17:51:23.89391+04:00",
        "Brackets": []
      },
      "CapitalGainsTax": null,
      "IncomeTax": null,
      "LumpsumpTax": null,
      "WealthTax": null
    },
    {
      "Name": "India",
      "Alpha2": "IN",
      "Alpha3": "IND",
      "CorporateTax": {
        "Rate": 43.68,
        "LastUpdated": "2022-11-14T17:51:23.8939295+04:00",
        "Brackets": []
      },
      "CapitalGainsTax": null,
      "IncomeTax": null,
      "LumpsumpTax": null,
      "WealthTax": null
    },
    {
      "Name": "Indonesia",
      "Alpha2": "ID",
      "Alpha3": "IDN",
      "CorporateTax": {
        "Rate": 25.00,
        "LastUpdated": "2022-11-14T17:51:23.89395+04:00",
        "Brackets": []
      },
      "CapitalGainsTax": null,
      "IncomeTax": null,
      "LumpsumpTax": null,
      "WealthTax": null
    },
    {
      "Name": "Iran",
      "Alpha2": "IR",
      "Alpha3": "IRN",
      "CorporateTax": {
        "Rate": 25.00,
        "LastUpdated": "2022-11-14T17:51:23.8939693+04:00",
        "Brackets": []
      },
      "CapitalGainsTax": null,
      "IncomeTax": null,
      "LumpsumpTax": null,
      "WealthTax": null
    },
    {
      "Name": "Iraq",
      "Alpha2": "IQ",
      "Alpha3": "IRQ",
      "CorporateTax": {
        "Rate": 15.00,
        "LastUpdated": "2022-11-14T17:51:23.8939852+04:00",
        "Brackets": []
      },
      "CapitalGainsTax": null,
      "IncomeTax": null,
      "LumpsumpTax": null,
      "WealthTax": null
    },
    {
      "Name": "Ireland",
      "Alpha2": "IE",
      "Alpha3": "IRL",
      "CorporateTax": {
        "Rate": 25.00,
        "LastUpdated": "2022-11-14T17:51:23.8940044+04:00",
        "Brackets": []
      },
      "CapitalGainsTax": null,
      "IncomeTax": null,
      "LumpsumpTax": null,
      "WealthTax": null
    },
    {
      "Name": "Israel",
      "Alpha2": "IL",
      "Alpha3": "ISR",
      "CorporateTax": {
        "Rate": 23.00,
        "LastUpdated": "2022-11-14T17:51:23.894023+04:00",
        "Brackets": []
      },
      "CapitalGainsTax": null,
      "IncomeTax": null,
      "LumpsumpTax": null,
      "WealthTax": null
    },
    {
      "Name": "Italy",
      "Alpha2": "IT",
      "Alpha3": "ITA",
      "CorporateTax": {
        "Rate": 24.00,
        "LastUpdated": "2022-11-14T17:51:23.8940479+04:00",
        "Brackets": []
      },
      "CapitalGainsTax": null,
      "IncomeTax": null,
      "LumpsumpTax": {
        "Amount": 100000.0,
        "Currency": null,
        "Rate": 0.0,
        "LastUpdated": "2022-11-14T17:51:23.9338271+04:00"
      },
      "WealthTax": null
    },
    {
      "Name": "Jamaica",
      "Alpha2": "JM",
      "Alpha3": "JAM",
      "CorporateTax": {
        "Rate": 33.00,
        "LastUpdated": "2022-11-14T17:51:23.8940807+04:00",
        "Brackets": []
      },
      "CapitalGainsTax": null,
      "IncomeTax": null,
      "LumpsumpTax": null,
      "WealthTax": null
    },
    {
      "Name": "Japan",
      "Alpha2": "JP",
      "Alpha3": "JPN",
      "CorporateTax": {
        "Rate": 30.62,
        "LastUpdated": "2022-11-14T17:51:23.8941058+04:00",
        "Brackets": []
      },
      "CapitalGainsTax": null,
      "IncomeTax": null,
      "LumpsumpTax": null,
      "WealthTax": null
    },
    {
      "Name": "Jordan",
      "Alpha2": "JO",
      "Alpha3": "JOR",
      "CorporateTax": {
        "Rate": 35.00,
        "LastUpdated": "2022-11-14T17:51:23.8941386+04:00",
        "Brackets": []
      },
      "CapitalGainsTax": null,
      "IncomeTax": null,
      "LumpsumpTax": null,
      "WealthTax": null
    },
    {
      "Name": "Kazakhstan",
      "Alpha2": "KZ",
      "Alpha3": "KAZ",
      "CorporateTax": {
        "Rate": 20.00,
        "LastUpdated": "2022-11-14T17:51:23.8941864+04:00",
        "Brackets": []
      },
      "CapitalGainsTax": null,
      "IncomeTax": null,
      "LumpsumpTax": null,
      "WealthTax": null
    },
    {
      "Name": "Kenya",
      "Alpha2": "KE",
      "Alpha3": "KEN",
      "CorporateTax": {
        "Rate": 30.00,
        "LastUpdated": "2022-11-14T17:51:23.8942583+04:00",
        "Brackets": []
      },
      "CapitalGainsTax": null,
      "IncomeTax": null,
      "LumpsumpTax": null,
      "WealthTax": null
    },
    {
      "Name": "Kuwait",
      "Alpha2": "KW",
      "Alpha3": "KWT",
      "CorporateTax": {
        "Rate": 15.00,
        "LastUpdated": "2022-11-14T17:51:23.8942995+04:00",
        "Brackets": []
      },
      "CapitalGainsTax": null,
      "IncomeTax": null,
      "LumpsumpTax": null,
      "WealthTax": null
    },
    {
      "Name": "Kyrgyzstan",
      "Alpha2": "KG",
      "Alpha3": "KGZ",
      "CorporateTax": {
        "Rate": 10.00,
        "LastUpdated": "2022-11-14T17:51:23.8943162+04:00",
        "Brackets": []
      },
      "CapitalGainsTax": null,
      "IncomeTax": null,
      "LumpsumpTax": null,
      "WealthTax": null
    },
    {
      "Name": "Latvia",
      "Alpha2": "LV",
      "Alpha3": "LVA",
      "CorporateTax": {
        "Rate": 20.00,
        "LastUpdated": "2022-11-14T17:51:23.8943416+04:00",
        "Brackets": []
      },
      "CapitalGainsTax": null,
      "IncomeTax": null,
      "LumpsumpTax": null,
      "WealthTax": null
    },
    {
      "Name": "Lebanon",
      "Alpha2": "LB",
      "Alpha3": "LBN",
      "CorporateTax": {
        "Rate": 17.00,
        "LastUpdated": "2022-11-14T17:51:23.8943629+04:00",
        "Brackets": []
      },
      "CapitalGainsTax": null,
      "IncomeTax": null,
      "LumpsumpTax": null,
      "WealthTax": null
    },
    {
      "Name": "Liberia",
      "Alpha2": "LR",
      "Alpha3": "LBR",
      "CorporateTax": {
        "Rate": 25.00,
        "LastUpdated": "2022-11-14T17:51:23.8943822+04:00",
        "Brackets": []
      },
      "CapitalGainsTax": null,
      "IncomeTax": null,
      "LumpsumpTax": null,
      "WealthTax": null
    },
    {
      "Name": "Libya",
      "Alpha2": "LY",
      "Alpha3": "LBY",
      "CorporateTax": {
        "Rate": 20.00,
        "LastUpdated": "2022-11-14T17:51:23.8944013+04:00",
        "Brackets": []
      },
      "CapitalGainsTax": null,
      "IncomeTax": null,
      "LumpsumpTax": null,
      "WealthTax": null
    },
    {
      "Name": "Liechtenstein",
      "Alpha2": "LI",
      "Alpha3": "LIE",
      "CorporateTax": {
        "Rate": 12.50,
        "LastUpdated": "2022-11-14T17:51:23.8944205+04:00",
        "Brackets": []
      },
      "CapitalGainsTax": null,
      "IncomeTax": null,
      "LumpsumpTax": null,
      "WealthTax": null
    },
    {
      "Name": "Lithuania",
      "Alpha2": "LT",
      "Alpha3": "LTU",
      "CorporateTax": {
        "Rate": 15.00,
        "LastUpdated": "2022-11-14T17:51:23.8944419+04:00",
        "Brackets": []
      },
      "CapitalGainsTax": null,
      "IncomeTax": null,
      "LumpsumpTax": null,
      "WealthTax": null
    },
    {
      "Name": "Luxembourg",
      "Alpha2": "LU",
      "Alpha3": "LUX",
      "CorporateTax": {
        "Rate": 24.94,
        "LastUpdated": "2022-11-14T17:51:23.8944606+04:00",
        "Brackets": []
      },
      "CapitalGainsTax": null,
      "IncomeTax": null,
      "LumpsumpTax": null,
      "WealthTax": null
    },
    {
      "Name": "Macao",
      "Alpha2": "MO",
      "Alpha3": "MAC",
      "CorporateTax": {
        "Rate": 12.00,
        "LastUpdated": "2022-11-14T17:51:23.8944802+04:00",
        "Brackets": []
      },
      "CapitalGainsTax": null,
      "IncomeTax": null,
      "LumpsumpTax": null,
      "WealthTax": null
    },
    {
      "Name": "Macedonia",
      "Alpha2": "MK",
      "Alpha3": "MKD",
      "CorporateTax": {
        "Rate": 10.00,
        "LastUpdated": "2022-11-14T17:51:23.8944998+04:00",
        "Brackets": []
      },
      "CapitalGainsTax": null,
      "IncomeTax": null,
      "LumpsumpTax": null,
      "WealthTax": null
    },
    {
      "Name": "Madagascar",
      "Alpha2": "MG",
      "Alpha3": "MDG",
      "CorporateTax": {
        "Rate": 20.00,
        "LastUpdated": "2022-11-14T17:51:23.8945192+04:00",
        "Brackets": []
      },
      "CapitalGainsTax": null,
      "IncomeTax": null,
      "LumpsumpTax": null,
      "WealthTax": null
    },
    {
      "Name": "Malaysia",
      "Alpha2": "MY",
      "Alpha3": "MYS",
      "CorporateTax": {
        "Rate": 24.00,
        "LastUpdated": "2022-11-14T17:51:23.89454+04:00",
        "Brackets": []
      },
      "CapitalGainsTax": null,
      "IncomeTax": null,
      "LumpsumpTax": null,
      "WealthTax": null
    },
    {
      "Name": "Maldives",
      "Alpha2": "MV",
      "Alpha3": "MDV",
      "CorporateTax": {
        "Rate": 15.00,
        "LastUpdated": "2022-11-14T17:51:23.8945622+04:00",
        "Brackets": []
      },
      "CapitalGainsTax": null,
      "IncomeTax": null,
      "LumpsumpTax": null,
      "WealthTax": null
    },
    {
      "Name": "Mali",
      "Alpha2": "ML",
      "Alpha3": "MLI",
      "CorporateTax": {
        "Rate": 30.00,
        "LastUpdated": "2022-11-14T17:51:23.8945819+04:00",
        "Brackets": []
      },
      "CapitalGainsTax": null,
      "IncomeTax": null,
      "LumpsumpTax": null,
      "WealthTax": null
    },
    {
      "Name": "Malta",
      "Alpha2": "MT",
      "Alpha3": "MLT",
      "CorporateTax": {
        "Rate": 35.00,
        "LastUpdated": "2022-11-14T17:51:23.8946026+04:00",
        "Brackets": []
      },
      "CapitalGainsTax": null,
      "IncomeTax": null,
      "LumpsumpTax": null,
      "WealthTax": null
    },
    {
      "Name": "Mauritius",
      "Alpha2": "MU",
      "Alpha3": "MUS",
      "CorporateTax": {
        "Rate": 15.00,
        "LastUpdated": "2022-11-14T17:51:23.8946242+04:00",
        "Brackets": []
      },
      "CapitalGainsTax": null,
      "IncomeTax": null,
      "LumpsumpTax": null,
      "WealthTax": null
    },
    {
      "Name": "Mexico",
      "Alpha2": "MX",
      "Alpha3": "MEX",
      "CorporateTax": {
        "Rate": 30.00,
        "LastUpdated": "2022-11-14T17:51:23.8946443+04:00",
        "Brackets": []
      },
      "CapitalGainsTax": null,
      "IncomeTax": null,
      "LumpsumpTax": null,
      "WealthTax": null
    },
    {
      "Name": "Moldova",
      "Alpha2": "MD",
      "Alpha3": "MDA",
      "CorporateTax": {
        "Rate": 12.00,
        "LastUpdated": "2022-11-14T17:51:23.8946685+04:00",
        "Brackets": []
      },
      "CapitalGainsTax": null,
      "IncomeTax": null,
      "LumpsumpTax": null,
      "WealthTax": null
    },
    {
      "Name": "Monaco",
      "Alpha2": "MC",
      "Alpha3": "MCO",
      "CorporateTax": {
        "Rate": 25.00,
        "LastUpdated": "2022-11-14T17:51:23.894703+04:00",
        "Brackets": []
      },
      "CapitalGainsTax": null,
      "IncomeTax": null,
      "LumpsumpTax": null,
      "WealthTax": null
    },
    {
      "Name": "Mongolia",
      "Alpha2": "MN",
      "Alpha3": "MNG",
      "CorporateTax": {
        "Rate": 25.00,
        "LastUpdated": "2022-11-14T17:51:23.8947369+04:00",
        "Brackets": []
      },
      "CapitalGainsTax": null,
      "IncomeTax": null,
      "LumpsumpTax": null,
      "WealthTax": null
    },
    {
      "Name": "Montenegro",
      "Alpha2": "ME",
      "Alpha3": "MNE",
      "CorporateTax": {
        "Rate": 15.00,
        "LastUpdated": "2022-11-14T17:51:23.894773+04:00",
        "Brackets": []
      },
      "CapitalGainsTax": null,
      "IncomeTax": null,
      "LumpsumpTax": null,
      "WealthTax": null
    },
    {
      "Name": "Montserrat",
      "Alpha2": "MS",
      "Alpha3": "MSR",
      "CorporateTax": null,
      "CapitalGainsTax": null,
      "IncomeTax": null,
      "LumpsumpTax": null,
      "WealthTax": null
    },
    {
      "Name": "Morocco",
      "Alpha2": "MA",
      "Alpha3": "MAR",
      "CorporateTax": {
        "Rate": 31.00,
        "LastUpdated": "2022-11-14T17:51:23.8948169+04:00",
        "Brackets": []
      },
      "CapitalGainsTax": null,
      "IncomeTax": null,
      "LumpsumpTax": null,
      "WealthTax": null
    },
    {
      "Name": "Mozambique",
      "Alpha2": "MZ",
      "Alpha3": "MOZ",
      "CorporateTax": {
        "Rate": 32.00,
        "LastUpdated": "2022-11-14T17:51:23.8948486+04:00",
        "Brackets": []
      },
      "CapitalGainsTax": null,
      "IncomeTax": null,
      "LumpsumpTax": null,
      "WealthTax": null
    },
    {
      "Name": "Myanmar",
      "Alpha2": "MM",
      "Alpha3": "MMR",
      "CorporateTax": {
        "Rate": 22.00,
        "LastUpdated": "2022-11-14T17:51:23.8948809+04:00",
        "Brackets": []
      },
      "CapitalGainsTax": null,
      "IncomeTax": null,
      "LumpsumpTax": null,
      "WealthTax": null
    },
    {
      "Name": "Namibia",
      "Alpha2": "NA",
      "Alpha3": "NAM",
      "CorporateTax": {
        "Rate": 25.00,
        "LastUpdated": "2022-11-14T17:51:23.8949069+04:00",
        "Brackets": []
      },
      "CapitalGainsTax": null,
      "IncomeTax": null,
      "LumpsumpTax": null,
      "WealthTax": null
    },
    {
      "Name": "Nepal",
      "Alpha2": "NP",
      "Alpha3": "NPL",
      "CorporateTax": {
        "Rate": 25.00,
        "LastUpdated": "2022-11-14T17:51:23.8949331+04:00",
        "Brackets": []
      },
      "CapitalGainsTax": null,
      "IncomeTax": null,
      "LumpsumpTax": null,
      "WealthTax": null
    },
    {
      "Name": "Netherlands",
      "Alpha2": "NL",
      "Alpha3": "NLD",
      "CorporateTax": {
        "Rate": 25.80,
        "LastUpdated": "2022-11-14T17:51:23.8949609+04:00",
        "Brackets": []
      },
      "CapitalGainsTax": null,
      "IncomeTax": null,
      "LumpsumpTax": null,
      "WealthTax": {
        "Rate": 1.68,
        "Base": 1020096.0,
        "Comments": "Yields only",
        "Currency": null,
        "LastUpdated": "2022-11-14T17:51:23.993322+04:00",
        "Brackets": []
      }
    },
    {
      "Name": "New Zealand",
      "Alpha2": "NZ",
      "Alpha3": "NZL",
      "CorporateTax": {
        "Rate": 28.00,
        "LastUpdated": "2022-11-14T17:51:23.8949827+04:00",
        "Brackets": []
      },
      "CapitalGainsTax": null,
      "IncomeTax": null,
      "LumpsumpTax": null,
      "WealthTax": null
    },
    {
      "Name": "Nicaragua",
      "Alpha2": "NI",
      "Alpha3": "NIC",
      "CorporateTax": {
        "Rate": 30.00,
        "LastUpdated": "2022-11-14T17:51:23.8950037+04:00",
        "Brackets": []
      },
      "CapitalGainsTax": null,
      "IncomeTax": null,
      "LumpsumpTax": null,
      "WealthTax": null
    },
    {
      "Name": "Niger",
      "Alpha2": "NE",
      "Alpha3": "NER",
      "CorporateTax": {
        "Rate": 30.00,
        "LastUpdated": "2022-11-14T17:51:23.895025+04:00",
        "Brackets": []
      },
      "CapitalGainsTax": null,
      "IncomeTax": null,
      "LumpsumpTax": null,
      "WealthTax": null
    },
    {
      "Name": "Nigeria",
      "Alpha2": "NG",
      "Alpha3": "NGA",
      "CorporateTax": {
        "Rate": 30.00,
        "LastUpdated": "2022-11-14T17:51:23.8950476+04:00",
        "Brackets": []
      },
      "CapitalGainsTax": null,
      "IncomeTax": null,
      "LumpsumpTax": null,
      "WealthTax": null
    },
    {
      "Name": "Norway",
      "Alpha2": "NO",
      "Alpha3": "NOR",
      "CorporateTax": {
        "Rate": 22.00,
        "LastUpdated": "2022-11-14T17:51:23.8950788+04:00",
        "Brackets": []
      },
      "CapitalGainsTax": null,
      "IncomeTax": null,
      "LumpsumpTax": null,
      "WealthTax": {
        "Rate": 0.95,
        "Base": 1500000.0,
        "Comments": "",
        "Currency": null,
        "LastUpdated": "2022-11-14T17:51:23.9934219+04:00",
        "Brackets": []
      }
    },
    {
      "Name": "Oman",
      "Alpha2": "OM",
      "Alpha3": "OMN",
      "CorporateTax": null,
      "CapitalGainsTax": null,
      "IncomeTax": null,
      "LumpsumpTax": null,
      "WealthTax": null
    },
    {
      "Name": "Pakistan",
      "Alpha2": "PK",
      "Alpha3": "PAK",
      "CorporateTax": {
        "Rate": 35.00,
        "LastUpdated": "2022-11-14T17:51:23.8951226+04:00",
        "Brackets": []
      },
      "CapitalGainsTax": null,
      "IncomeTax": null,
      "LumpsumpTax": null,
      "WealthTax": null
    },
    {
      "Name": "Palau",
      "Alpha2": "PW",
      "Alpha3": "PLW",
      "CorporateTax": {
        "Rate": 0.00,
        "LastUpdated": "2022-11-14T17:51:23.895144+04:00",
        "Brackets": []
      },
      "CapitalGainsTax": null,
      "IncomeTax": null,
      "LumpsumpTax": null,
      "WealthTax": null
    },
    {
      "Name": "Palestine",
      "Alpha2": "PS",
      "Alpha3": "PSE",
      "CorporateTax": {
        "Rate": 15.00,
        "LastUpdated": "2022-11-14T17:51:23.8951653+04:00",
        "Brackets": []
      },
      "CapitalGainsTax": null,
      "IncomeTax": null,
      "LumpsumpTax": null,
      "WealthTax": null
    },
    {
      "Name": "Panama",
      "Alpha2": "PA",
      "Alpha3": "PAN",
      "CorporateTax": {
        "Rate": 25.00,
        "LastUpdated": "2022-11-14T17:51:23.8951871+04:00",
        "Brackets": []
      },
      "CapitalGainsTax": null,
      "IncomeTax": null,
      "LumpsumpTax": null,
      "WealthTax": null
    },
    {
      "Name": "Papua New Guinea",
      "Alpha2": "PG",
      "Alpha3": "PNG",
      "CorporateTax": {
        "Rate": 30.00,
        "LastUpdated": "2022-11-14T17:51:23.8952096+04:00",
        "Brackets": []
      },
      "CapitalGainsTax": null,
      "IncomeTax": null,
      "LumpsumpTax": null,
      "WealthTax": null
    },
    {
      "Name": "Paraguay",
      "Alpha2": "PY",
      "Alpha3": "PRY",
      "CorporateTax": {
        "Rate": 10.00,
        "LastUpdated": "2022-11-14T17:51:23.8952324+04:00",
        "Brackets": []
      },
      "CapitalGainsTax": null,
      "IncomeTax": null,
      "LumpsumpTax": null,
      "WealthTax": null
    },
    {
      "Name": "Peru",
      "Alpha2": "PE",
      "Alpha3": "PER",
      "CorporateTax": {
        "Rate": 29.50,
        "LastUpdated": "2022-11-14T17:51:23.8952544+04:00",
        "Brackets": []
      },
      "CapitalGainsTax": null,
      "IncomeTax": null,
      "LumpsumpTax": null,
      "WealthTax": null
    },
    {
      "Name": "Philippines",
      "Alpha2": "PH",
      "Alpha3": "PHL",
      "CorporateTax": {
        "Rate": 25.00,
        "LastUpdated": "2022-11-14T17:51:23.8952766+04:00",
        "Brackets": []
      },
      "CapitalGainsTax": null,
      "IncomeTax": null,
      "LumpsumpTax": null,
      "WealthTax": null
    },
    {
      "Name": "Poland",
      "Alpha2": "PL",
      "Alpha3": "POL",
      "CorporateTax": {
        "Rate": 19.00,
        "LastUpdated": "2022-11-14T17:51:23.8952987+04:00",
        "Brackets": []
      },
      "CapitalGainsTax": null,
      "IncomeTax": null,
      "LumpsumpTax": null,
      "WealthTax": null
    },
    {
      "Name": "Portugal",
      "Alpha2": "PT",
      "Alpha3": "PRT",
      "CorporateTax": {
        "Rate": 21.00,
        "LastUpdated": "2022-11-14T17:51:23.8953221+04:00",
        "Brackets": []
      },
      "CapitalGainsTax": null,
      "IncomeTax": null,
      "LumpsumpTax": null,
      "WealthTax": null
    },
    {
      "Name": "Puerto Rico",
      "Alpha2": "PR",
      "Alpha3": "PRI",
      "CorporateTax": {
        "Rate": 18.50,
        "LastUpdated": "2022-11-14T17:51:23.8953446+04:00",
        "Brackets": []
      },
      "CapitalGainsTax": null,
      "IncomeTax": null,
      "LumpsumpTax": null,
      "WealthTax": null
    },
    {
      "Name": "Qatar",
      "Alpha2": "QA",
      "Alpha3": "QAT",
      "CorporateTax": {
        "Rate": 10.00,
        "LastUpdated": "2022-11-14T17:51:23.8953668+04:00",
        "Brackets": []
      },
      "CapitalGainsTax": null,
      "IncomeTax": null,
      "LumpsumpTax": null,
      "WealthTax": null
    },
    {
      "Name": "Romania",
      "Alpha2": "RO",
      "Alpha3": "ROU",
      "CorporateTax": {
        "Rate": 16.00,
        "LastUpdated": "2022-11-14T17:51:23.8953887+04:00",
        "Brackets": []
      },
      "CapitalGainsTax": null,
      "IncomeTax": null,
      "LumpsumpTax": null,
      "WealthTax": null
    },
    {
      "Name": "Russia",
      "Alpha2": "RU",
      "Alpha3": "RUS",
      "CorporateTax": {
        "Rate": 15.00,
        "LastUpdated": "2022-11-14T17:51:23.8954687+04:00",
        "Brackets": []
      },
      "CapitalGainsTax": null,
      "IncomeTax": null,
      "LumpsumpTax": null,
      "WealthTax": null
    },
    {
      "Name": "Rwanda",
      "Alpha2": "RW",
      "Alpha3": "RWA",
      "CorporateTax": {
        "Rate": 30.00,
        "LastUpdated": "2022-11-14T17:51:23.8954913+04:00",
        "Brackets": []
      },
      "CapitalGainsTax": null,
      "IncomeTax": null,
      "LumpsumpTax": null,
      "WealthTax": null
    },
    {
      "Name": "Saint Vincent and the Grenadines",
      "Alpha2": "VC",
      "Alpha3": "VCT",
      "CorporateTax": {
        "Rate": 30.00,
        "LastUpdated": "2022-11-14T17:51:23.8965481+04:00",
        "Brackets": []
      },
      "CapitalGainsTax": null,
      "IncomeTax": null,
      "LumpsumpTax": null,
      "WealthTax": null
    },
    {
      "Name": "Samoa",
      "Alpha2": "WS",
      "Alpha3": "WSM",
      "CorporateTax": {
        "Rate": 27.00,
        "LastUpdated": "2022-11-14T17:51:23.8965776+04:00",
        "Brackets": []
      },
      "CapitalGainsTax": null,
      "IncomeTax": null,
      "LumpsumpTax": null,
      "WealthTax": null
    },
    {
      "Name": "San Marino",
      "Alpha2": "SM",
      "Alpha3": "SMR",
      "CorporateTax": {
        "Rate": 17.00,
        "LastUpdated": "2022-11-14T17:51:23.8955135+04:00",
        "Brackets": []
      },
      "CapitalGainsTax": null,
      "IncomeTax": null,
      "LumpsumpTax": null,
      "WealthTax": null
    },
    {
      "Name": "Sao Tome and Principe",
      "Alpha2": "ST",
      "Alpha3": "STP",
      "CorporateTax": {
        "Rate": 10.00,
        "LastUpdated": "2022-11-14T17:51:23.8966043+04:00",
        "Brackets": []
      },
      "CapitalGainsTax": null,
      "IncomeTax": null,
      "LumpsumpTax": null,
      "WealthTax": null
    },
    {
      "Name": "Saudi Arabia",
      "Alpha2": "SA",
      "Alpha3": "SAU",
      "CorporateTax": {
        "Rate": 20.00,
        "LastUpdated": "2022-11-14T17:51:23.8955366+04:00",
        "Brackets": []
      },
      "CapitalGainsTax": null,
      "IncomeTax": null,
      "LumpsumpTax": null,
      "WealthTax": null
    },
    {
      "Name": "Senegal",
      "Alpha2": "SN",
      "Alpha3": "SEN",
      "CorporateTax": {
        "Rate": 30.00,
        "LastUpdated": "2022-11-14T17:51:23.895559+04:00",
        "Brackets": []
      },
      "CapitalGainsTax": null,
      "IncomeTax": null,
      "LumpsumpTax": null,
      "WealthTax": null
    },
    {
      "Name": "Serbia",
      "Alpha2": "RS",
      "Alpha3": "SRB",
      "CorporateTax": {
        "Rate": 15.00,
        "LastUpdated": "2022-11-14T17:51:23.8955815+04:00",
        "Brackets": []
      },
      "CapitalGainsTax": null,
      "IncomeTax": null,
      "LumpsumpTax": null,
      "WealthTax": null
    },
    {
      "Name": "Seychelles",
      "Alpha2": "SC",
      "Alpha3": "SYC",
      "CorporateTax": {
        "Rate": 30.00,
        "LastUpdated": "2022-11-14T17:51:23.8956058+04:00",
        "Brackets": []
      },
      "CapitalGainsTax": null,
      "IncomeTax": null,
      "LumpsumpTax": null,
      "WealthTax": null
    },
    {
      "Name": "Sierra Leone",
      "Alpha2": "SL",
      "Alpha3": "SLE",
      "CorporateTax": {
        "Rate": 30.00,
        "LastUpdated": "2022-11-14T17:51:23.8956326+04:00",
        "Brackets": []
      },
      "CapitalGainsTax": null,
      "IncomeTax": null,
      "LumpsumpTax": null,
      "WealthTax": null
    },
    {
      "Name": "Singapore",
      "Alpha2": "SG",
      "Alpha3": "SGP",
      "CorporateTax": {
        "Rate": 17.00,
        "LastUpdated": "2022-11-14T17:51:23.8956559+04:00",
        "Brackets": []
      },
      "CapitalGainsTax": null,
      "IncomeTax": null,
      "LumpsumpTax": null,
      "WealthTax": null
    },
    {
      "Name": "Slovakia",
      "Alpha2": "SK",
      "Alpha3": "SVK",
      "CorporateTax": {
        "Rate": 21.00,
        "LastUpdated": "2022-11-14T17:51:23.8956784+04:00",
        "Brackets": []
      },
      "CapitalGainsTax": null,
      "IncomeTax": null,
      "LumpsumpTax": null,
      "WealthTax": null
    },
    {
      "Name": "Slovenia",
      "Alpha2": "SI",
      "Alpha3": "SVN",
      "CorporateTax": {
        "Rate": 19.00,
        "LastUpdated": "2022-11-14T17:51:23.8957011+04:00",
        "Brackets": []
      },
      "CapitalGainsTax": null,
      "IncomeTax": null,
      "LumpsumpTax": null,
      "WealthTax": null
    },
    {
      "Name": "Somalia",
      "Alpha2": "SO",
      "Alpha3": "SOM",
      "CorporateTax": {
        "Rate": 30.00,
        "LastUpdated": "2022-11-14T17:51:23.8957256+04:00",
        "Brackets": []
      },
      "CapitalGainsTax": null,
      "IncomeTax": null,
      "LumpsumpTax": null,
      "WealthTax": null
    },
    {
      "Name": "South Africa",
      "Alpha2": "ZA",
      "Alpha3": "ZAF",
      "CorporateTax": {
        "Rate": 28.00,
        "LastUpdated": "2022-11-14T17:51:23.8957509+04:00",
        "Brackets": []
      },
      "CapitalGainsTax": null,
      "IncomeTax": null,
      "LumpsumpTax": null,
      "WealthTax": null
    },
    {
      "Name": "South Georgia",
      "Alpha2": "GS",
      "Alpha3": "SGS",
      "CorporateTax": {
        "Rate": 15.00,
        "LastUpdated": "2022-11-14T17:51:23.8957772+04:00",
        "Brackets": []
      },
      "CapitalGainsTax": null,
      "IncomeTax": null,
      "LumpsumpTax": null,
      "WealthTax": null
    },
    {
      "Name": "South Korea",
      "Alpha2": "KR",
      "Alpha3": "KOR",
      "CorporateTax": {
        "Rate": 25.00,
        "LastUpdated": "2022-11-14T17:51:23.89428+04:00",
        "Brackets": []
      },
      "CapitalGainsTax": null,
      "IncomeTax": null,
      "LumpsumpTax": null,
      "WealthTax": null
    },
    {
      "Name": "South Sudan",
      "Alpha2": "SS",
      "Alpha3": "SSD",
      "CorporateTax": {
        "Rate": 35.00,
        "LastUpdated": "2022-11-14T17:51:23.8958005+04:00",
        "Brackets": []
      },
      "CapitalGainsTax": null,
      "IncomeTax": null,
      "LumpsumpTax": null,
      "WealthTax": null
    },
    {
      "Name": "Spain",
      "Alpha2": "ES",
      "Alpha3": "ESP",
      "CorporateTax": {
        "Rate": 25.00,
        "LastUpdated": "2022-11-14T17:51:23.8958232+04:00",
        "Brackets": []
      },
      "CapitalGainsTax": null,
      "IncomeTax": null,
      "LumpsumpTax": null,
      "WealthTax": {
        "Rate": 3.50,
        "Base": 10000000.0,
        "Comments": "",
        "Currency": null,
        "LastUpdated": "2022-11-14T17:51:23.9941372+04:00",
        "Brackets": []
      }
    },
    {
      "Name": "Sri Lanka",
      "Alpha2": "LK",
      "Alpha3": "LKA",
      "CorporateTax": {
        "Rate": 30.00,
        "LastUpdated": "2022-11-14T17:51:23.8958462+04:00",
        "Brackets": []
      },
      "CapitalGainsTax": null,
      "IncomeTax": null,
      "LumpsumpTax": null,
      "WealthTax": null
    },
    {
      "Name": "Sudan",
      "Alpha2": "SD",
      "Alpha3": "SDN",
      "CorporateTax": {
        "Rate": 35.00,
        "LastUpdated": "2022-11-14T17:51:23.8958696+04:00",
        "Brackets": []
      },
      "CapitalGainsTax": null,
      "IncomeTax": null,
      "LumpsumpTax": null,
      "WealthTax": null
    },
    {
      "Name": "Svalbard",
      "Alpha2": "SJ",
      "Alpha3": "SJM",
      "CorporateTax": {
        "Rate": 22.00,
        "LastUpdated": "2022-11-14T17:51:23.8958961+04:00",
        "Brackets": []
      },
      "CapitalGainsTax": null,
      "IncomeTax": null,
      "LumpsumpTax": null,
      "WealthTax": null
    },
    {
      "Name": "Sweden",
      "Alpha2": "SE",
      "Alpha3": "SWE",
      "CorporateTax": {
        "Rate": 20.60,
        "LastUpdated": "2022-11-14T17:51:23.8959195+04:00",
        "Brackets": []
      },
      "CapitalGainsTax": null,
      "IncomeTax": null,
      "LumpsumpTax": null,
      "WealthTax": null
    },
    {
      "Name": "Switzerland",
      "Alpha2": "CH",
      "Alpha3": "CHE",
      "CorporateTax": {
        "Rate": 8.50,
        "LastUpdated": "2022-11-14T17:51:23.895945+04:00",
        "Brackets": []
      },
      "CapitalGainsTax": null,
      "IncomeTax": null,
      "LumpsumpTax": {
        "Amount": 400000.0,
        "Currency": null,
        "Rate": 0.0,
        "LastUpdated": "2022-11-14T17:51:23.9352553+04:00"
      },
      "WealthTax": {
        "Rate": 0.30,
        "Base": 3158000.0,
        "Comments": "Data from Zurich",
        "Currency": null,
        "LastUpdated": "2022-11-14T17:51:23.9943386+04:00",
        "Brackets": []
      }
    },
    {
      "Name": "Taiwan",
      "Alpha2": "TW",
      "Alpha3": "TWN",
      "CorporateTax": {
        "Rate": 20.00,
        "LastUpdated": "2022-11-14T17:51:23.8959696+04:00",
        "Brackets": []
      },
      "CapitalGainsTax": null,
      "IncomeTax": null,
      "LumpsumpTax": null,
      "WealthTax": null
    },
    {
      "Name": "Tajikistan",
      "Alpha2": "TJ",
      "Alpha3": "TJK",
      "CorporateTax": {
        "Rate": 25.00,
        "LastUpdated": "2022-11-14T17:51:23.8959966+04:00",
        "Brackets": []
      },
      "CapitalGainsTax": null,
      "IncomeTax": null,
      "LumpsumpTax": null,
      "WealthTax": null
    },
    {
      "Name": "Tanzania",
      "Alpha2": "TZ",
      "Alpha3": "TZA",
      "CorporateTax": {
        "Rate": 30.00,
        "LastUpdated": "2022-11-14T17:51:23.8960207+04:00",
        "Brackets": []
      },
      "CapitalGainsTax": null,
      "IncomeTax": null,
      "LumpsumpTax": null,
      "WealthTax": null
    },
    {
      "Name": "Thailand",
      "Alpha2": "TH",
      "Alpha3": "THA",
      "CorporateTax": {
        "Rate": 20.00,
        "LastUpdated": "2022-11-14T17:51:23.8960486+04:00",
        "Brackets": []
      },
      "CapitalGainsTax": null,
      "IncomeTax": null,
      "LumpsumpTax": null,
      "WealthTax": null
    },
    {
      "Name": "Timor-Leste",
      "Alpha2": "TL",
      "Alpha3": "TLS",
      "CorporateTax": {
        "Rate": 10.00,
        "LastUpdated": "2022-11-14T17:51:23.8966303+04:00",
        "Brackets": []
      },
      "CapitalGainsTax": null,
      "IncomeTax": null,
      "LumpsumpTax": null,
      "WealthTax": null
    },
    {
      "Name": "Togo",
      "Alpha2": "TG",
      "Alpha3": "TGO",
      "CorporateTax": {
        "Rate": 27.00,
        "LastUpdated": "2022-11-14T17:51:23.8960727+04:00",
        "Brackets": []
      },
      "CapitalGainsTax": null,
      "IncomeTax": null,
      "LumpsumpTax": null,
      "WealthTax": null
    },
    {
      "Name": "Tonga",
      "Alpha2": "TO",
      "Alpha3": "TON",
      "CorporateTax": {
        "Rate": 25.00,
        "LastUpdated": "2022-11-14T17:51:23.8960997+04:00",
        "Brackets": []
      },
      "CapitalGainsTax": null,
      "IncomeTax": null,
      "LumpsumpTax": null,
      "WealthTax": null
    },
    {
      "Name": "Trinidad and Tobago",
      "Alpha2": "TT",
      "Alpha3": "TTO",
      "CorporateTax": {
        "Rate": 30.00,
        "LastUpdated": "2022-11-14T17:51:23.8961251+04:00",
        "Brackets": []
      },
      "CapitalGainsTax": null,
      "IncomeTax": null,
      "LumpsumpTax": null,
      "WealthTax": null
    },
    {
      "Name": "Tunisia",
      "Alpha2": "TN",
      "Alpha3": "TUN",
      "CorporateTax": {
        "Rate": 15.00,
        "LastUpdated": "2022-11-14T17:51:23.8961489+04:00",
        "Brackets": []
      },
      "CapitalGainsTax": null,
      "IncomeTax": null,
      "LumpsumpTax": null,
      "WealthTax": null
    },
    {
      "Name": "Turkey",
      "Alpha2": "TR",
      "Alpha3": "TUR",
      "CorporateTax": {
        "Rate": 20.00,
        "LastUpdated": "2022-11-14T17:51:23.8961766+04:00",
        "Brackets": []
      },
      "CapitalGainsTax": null,
      "IncomeTax": null,
      "LumpsumpTax": null,
      "WealthTax": null
    },
    {
      "Name": "Turkmenistan",
      "Alpha2": "TM",
      "Alpha3": "TKM",
      "CorporateTax": {
        "Rate": 20.00,
        "LastUpdated": "2022-11-14T17:51:23.8962017+04:00",
        "Brackets": []
      },
      "CapitalGainsTax": null,
      "IncomeTax": null,
      "LumpsumpTax": null,
      "WealthTax": null
    },
    {
      "Name": "Tuvalu",
      "Alpha2": "TV",
      "Alpha3": "TUV",
      "CorporateTax": {
        "Rate": 30.00,
        "LastUpdated": "2022-11-14T17:51:23.896659+04:00",
        "Brackets": []
      },
      "CapitalGainsTax": null,
      "IncomeTax": null,
      "LumpsumpTax": null,
      "WealthTax": null
    },
    {
      "Name": "Uganda",
      "Alpha2": "UG",
      "Alpha3": "UGA",
      "CorporateTax": {
        "Rate": 30.00,
        "LastUpdated": "2022-11-14T17:51:23.8962262+04:00",
        "Brackets": []
      },
      "CapitalGainsTax": null,
      "IncomeTax": null,
      "LumpsumpTax": null,
      "WealthTax": null
    },
    {
      "Name": "Ukraine",
      "Alpha2": "UA",
      "Alpha3": "UKR",
      "CorporateTax": {
        "Rate": 18.00,
        "LastUpdated": "2022-11-14T17:51:23.8962507+04:00",
        "Brackets": []
      },
      "CapitalGainsTax": null,
      "IncomeTax": null,
      "LumpsumpTax": null,
      "WealthTax": null
    },
    {
      "Name": "United Arab Emirates",
      "Alpha2": "AE",
      "Alpha3": "ARE",
      "CorporateTax": {
        "Rate": 50.00,
        "LastUpdated": "2022-11-14T17:51:23.8962825+04:00",
        "Brackets": []
      },
      "CapitalGainsTax": null,
      "IncomeTax": null,
      "LumpsumpTax": null,
      "WealthTax": null
    },
    {
      "Name": "United Kingdom",
      "Alpha2": "GB",
      "Alpha3": "GBR",
      "CorporateTax": {
        "Rate": 19.00,
        "LastUpdated": "2022-11-14T17:51:23.896307+04:00",
        "Brackets": []
      },
      "CapitalGainsTax": null,
      "IncomeTax": null,
      "LumpsumpTax": null,
      "WealthTax": null
    },
    {
      "Name": "United States",
      "Alpha2": "US",
      "Alpha3": "USA",
      "CorporateTax": {
        "Rate": 21.00,
        "LastUpdated": "2022-11-14T17:51:23.8963326+04:00",
        "Brackets": []
      },
      "CapitalGainsTax": null,
      "IncomeTax": null,
      "LumpsumpTax": null,
      "WealthTax": null
    },
    {
      "Name": "Uruguay",
      "Alpha2": "UY",
      "Alpha3": "URY",
      "CorporateTax": {
        "Rate": 25.00,
        "LastUpdated": "2022-11-14T17:51:23.8963597+04:00",
        "Brackets": []
      },
      "CapitalGainsTax": null,
      "IncomeTax": null,
      "LumpsumpTax": null,
      "WealthTax": null
    },
    {
      "Name": "Uzbekistan",
      "Alpha2": "UZ",
      "Alpha3": "UZB",
      "CorporateTax": {
        "Rate": 15.00,
        "LastUpdated": "2022-11-14T17:51:23.8963855+04:00",
        "Brackets": []
      },
      "CapitalGainsTax": null,
      "IncomeTax": null,
      "LumpsumpTax": null,
      "WealthTax": null
    },
    {
      "Name": "Vanuatu",
      "Alpha2": "VU",
      "Alpha3": "VUT",
      "CorporateTax": {
        "Rate": 0.00,
        "LastUpdated": "2022-11-14T17:51:23.8967015+04:00",
        "Brackets": []
      },
      "CapitalGainsTax": null,
      "IncomeTax": null,
      "LumpsumpTax": null,
      "WealthTax": null
    },
    {
      "Name": "Venezuela",
      "Alpha2": "VE",
      "Alpha3": "VEN",
      "CorporateTax": {
        "Rate": 34.00,
        "LastUpdated": "2022-11-14T17:51:23.8964119+04:00",
        "Brackets": []
      },
      "CapitalGainsTax": null,
      "IncomeTax": null,
      "LumpsumpTax": null,
      "WealthTax": null
    },
    {
      "Name": "Vietnam",
      "Alpha2": "VN",
      "Alpha3": "VNM",
      "CorporateTax": {
        "Rate": 20.00,
        "LastUpdated": "2022-11-14T17:51:23.8964417+04:00",
        "Brackets": []
      },
      "CapitalGainsTax": null,
      "IncomeTax": null,
      "LumpsumpTax": null,
      "WealthTax": null
    },
    {
      "Name": "Yemen",
      "Alpha2": "YE",
      "Alpha3": "YEM",
      "CorporateTax": {
        "Rate": 20.00,
        "LastUpdated": "2022-11-14T17:51:23.8964667+04:00",
        "Brackets": []
      },
      "CapitalGainsTax": null,
      "IncomeTax": null,
      "LumpsumpTax": null,
      "WealthTax": null
    },
    {
      "Name": "Zambia",
      "Alpha2": "ZM",
      "Alpha3": "ZMB",
      "CorporateTax": {
        "Rate": 40.00,
        "LastUpdated": "2022-11-14T17:51:23.8964932+04:00",
        "Brackets": []
      },
      "CapitalGainsTax": null,
      "IncomeTax": null,
      "LumpsumpTax": null,
      "WealthTax": null
    },
    {
      "Name": "Zimbabwe",
      "Alpha2": "ZW",
      "Alpha3": "ZWE",
      "CorporateTax": {
        "Rate": 24.72,
        "LastUpdated": "2022-11-14T17:51:23.8965222+04:00",
        "Brackets": []
      },
      "CapitalGainsTax": null,
      "IncomeTax": null,
      "LumpsumpTax": null,
      "WealthTax": null
    }
  ]
}